soufflesankey/__init__.py
soufflesankey/sankey.py
soufflesankey-0.2.0.dist-info/LICENSE
soufflesankey-0.2.0.dist-info/METADATA
soufflesankey-0.2.0.dist-info/WHEEL
soufflesankey-0.2.0.dist-info/top_level.txt
soufflesankey-0.2.0.dist-info/RECORD
