Metadata-Version: 2.1
Name: soufflesankey
Version: 0.2.0
Summary: A Python package for creating Sankey diagrams with a focus on mobile app analytics
Home-page: https://github.com/S0uffle/soufflesankey
Author: Souffle2
Author-email: 0229gnoliah@gmail.com
Classifier: Programming Language :: Python :: 3
Classifier: License :: OSI Approved :: MIT License
Classifier: Operating System :: OS Independent
Requires-Python: >=3.6
License-File: LICENSE
Requires-Dist: plotly
Requires-Dist: pandas
Requires-Dist: numpy
